Metadata-Version: 1.2
Name: easy-i3-neovim-nav
Version: 1.7
Summary: Quickly navigate and resize i3wm windows and Neovim splits with the same keybindings
Home-page: http://github.com/tom-anders/easy_i3_neovim_nav
Author: Tom Praschan
Author-email: tom@praschan.de
License: GPLv3
Project-URL: Bug Tracker, http://github.com/tom-anders/easy_i3_neovim_nav/issues
Keywords: i3wm vim nvim neovim
Platform: UNKNOWN
Classifier: Programming Language :: Python :: 3
Classifier: License :: OSI Approved :: GNU General Public License v3 (GPLv3)
Classifier: Operating System :: OS Independent
